{
  "Yahtzee.dll": {
    "/Users/anton/School/Year 2/2dv610/assignment-1/yahtzee/Yahtzee/Program.cs": {
      "Yahtzee.Program": {
        "System.Void Yahtzee.Program::Main(System.String[])": {
          "Lines": {
            "8": 0,
            "9": 0,
            "10": 0
          },
          "Branches": []
        }
      }
    },
    "/Users/anton/School/Year 2/2dv610/assignment-1/yahtzee/Yahtzee/model/AllOptionStrategy.cs": {
      "Yahtzee.model.AllOptionStrategy": {
        "System.Collections.Generic.List`1<Yahtzee.model.Category> Yahtzee.model.AllOptionStrategy::GetOptions(Yahtzee.model.Dice)": {
          "Lines": {
            "14": 4,
            "15": 5,
            "16": 3,
            "17": 3
          },
          "Branches": [
            {
              "Line": 15,
              "Offset": 7,
              "EndOffset": 9,
              "Path": 0,
              "Ordinal": 0,
              "Hits": 1
            },
            {
              "Line": 15,
              "Offset": 7,
              "EndOffset": 15,
              "Path": 1,
              "Ordinal": 1,
              "Hits": 3
            }
          ]
        }
      },
      "Yahtzee.model.AllOptionStrategy/Pair": {
        "System.Int32 Yahtzee.model.AllOptionStrategy/Pair::GetValue()": {
          "Lines": {
            "11": 0
          },
          "Branches": []
        }
      }
    },
    "/Users/anton/School/Year 2/2dv610/assignment-1/yahtzee/Yahtzee/model/Dice.cs": {
      "Yahtzee.model.Dice": {
        "System.Void Yahtzee.model.Dice::Throw()": {
          "Lines": {
            "31": 4
          },
          "Branches": []
        },
        "System.Void Yahtzee.model.Dice::KeepDie(Yahtzee.model.Dice/DiceList)": {
          "Lines": {
            "33": 7
          },
          "Branches": []
        },
        "System.Collections.Generic.List`1<System.Int32> Yahtzee.model.Dice::GetValues()": {
          "Lines": {
            "35": 12
          },
          "Branches": [
            {
              "Line": 35,
              "Offset": 12,
              "EndOffset": 14,
              "Path": 0,
              "Ordinal": 0,
              "Hits": 1
            },
            {
              "Line": 35,
              "Offset": 12,
              "EndOffset": 37,
              "Path": 1,
              "Ordinal": 1,
              "Hits": 2
            }
          ]
        },
        "System.Collections.Generic.List`1<Yahtzee.model.Die> Yahtzee.model.Dice::GetAvailableDice()": {
          "Lines": {
            "37": 4
          },
          "Branches": []
        },
        "System.Void Yahtzee.model.Dice::ThrowDie(Yahtzee.model.Die)": {
          "Lines": {
            "39": 8
          },
          "Branches": []
        },
        "System.Void Yahtzee.model.Dice::.ctor(Yahtzee.model.Die,Yahtzee.model.Die,Yahtzee.model.Die,Yahtzee.model.Die,Yahtzee.model.Die)": {
          "Lines": {
            "20": 9,
            "21": 9,
            "22": 9,
            "23": 9,
            "24": 9,
            "25": 9,
            "26": 9,
            "27": 9,
            "28": 9,
            "29": 9
          },
          "Branches": []
        }
      }
    },
    "/Users/anton/School/Year 2/2dv610/assignment-1/yahtzee/Yahtzee/model/DieImplemented.cs": {
      "Yahtzee.model.DieImplemented": {
        "System.Int32 Yahtzee.model.DieImplemented::GetValue()": {
          "Lines": {
            "17": 102009
          },
          "Branches": []
        },
        "System.Void Yahtzee.model.DieImplemented::Throw()": {
          "Lines": {
            "19": 102014
          },
          "Branches": []
        },
        "System.Void Yahtzee.model.DieImplemented::.ctor()": {
          "Lines": {
            "11": 14,
            "12": 14,
            "13": 14,
            "14": 14,
            "15": 14
          },
          "Branches": []
        }
      }
    }
  }
}